js2xml/__init__.py
js2xml/__main__.py
js2xml/jsonlike.py
js2xml/lexer.py
js2xml/lextab.py
js2xml/log.py
js2xml/parser.py
js2xml/xmlvisitor.py
js2xml/yacctab.py
js2xml/utils/__init__.py
js2xml/utils/objects.py
js2xml/utils/vars.py
js2xml-0.3.1.dist-info/DESCRIPTION.rst
js2xml-0.3.1.dist-info/METADATA
js2xml-0.3.1.dist-info/RECORD
js2xml-0.3.1.dist-info/WHEEL
js2xml-0.3.1.dist-info/metadata.json
js2xml-0.3.1.dist-info/top_level.txt
